snic-0.1.0.dist-info/METADATA
snic-0.1.0.dist-info/WHEEL
snic-0.1.0.dist-info/licenses/LICENSE
snic/__init__.py
snic/snic.abi3.so
snic-0.1.0.dist-info/RECORD
