Metadata-Version: 2.4
Name: snic
Version: 0.1.0
Classifier: Development Status :: 3 - Alpha
Classifier: Intended Audience :: Developers
Classifier: Intended Audience :: Science/Research
Classifier: Programming Language :: Python :: 3 :: Only
Classifier: Programming Language :: Python :: 3.8
Classifier: Programming Language :: Python :: 3.9
Classifier: Programming Language :: Python :: 3.10
Classifier: Programming Language :: Python :: 3.11
Classifier: Programming Language :: Python :: 3.12
Classifier: Programming Language :: Python :: Implementation :: CPython
Classifier: Programming Language :: Python :: Implementation :: PyPy
Classifier: Programming Language :: Rust
Classifier: Topic :: Scientific/Engineering
Classifier: Topic :: Scientific/Engineering :: Information Analysis
Classifier: Topic :: Software Development :: Libraries :: Python Modules
License-File: LICENSE
Summary: High-performance library for efficient ranking of large datasets using sparse comparison networks
Keywords: ranking,comparison,sparse-network,algorithm,data-analysis,machine-learning
Author-email: Arthur Ryzhak <ryzhakar@gmail.com>
License: AGPLv3
Requires-Python: >=3.8
Project-URL: Homepage, https://github.com/ryzhakar/snic-rs
Project-URL: Repository, https://github.com/ryzhakar/snic-rs.git
Project-URL: Bug Tracker, https://github.com/ryzhakar/snic-rs/issues
Project-URL: Documentation, https://github.com/ryzhakar/snic-rs/wiki
